README.rst
setup.py
dg_sdk/__init__.py
dg_sdk/dg_client.py
dg_sdk/dg_tools.py
dg_sdk.egg-info/PKG-INFO
dg_sdk.egg-info/SOURCES.txt
dg_sdk.egg-info/dependency_links.txt
dg_sdk.egg-info/requires.txt
dg_sdk.egg-info/top_level.txt
dg_sdk/core/__init__.py
dg_sdk/core/api_request.py
dg_sdk/core/api_request_v1.py
dg_sdk/core/common_util.py
dg_sdk/core/log_util.py
dg_sdk/core/mer_config.py
dg_sdk/core/param_handler.py
dg_sdk/core/request_tools.py
dg_sdk/core/rsa_utils.py
dg_sdk/request/__init__.py
dg_sdk/request/request_api_urls.py
dg_sdk/request/v2_bank_balance_query_request.py
dg_sdk/request/v2_bill_ent_changestat_request.py
dg_sdk/request/v2_bill_ent_create_request.py
dg_sdk/request/v2_bill_ent_payer_create_request.py
dg_sdk/request/v2_bill_ent_payer_delete_request.py
dg_sdk/request/v2_bill_ent_payer_query_request.py
dg_sdk/request/v2_bill_ent_payer_update_request.py
dg_sdk/request/v2_bill_ent_query_request.py
dg_sdk/request/v2_bill_ent_refund_query_request.py
dg_sdk/request/v2_bill_ent_refund_request.py
dg_sdk/request/v2_coupon_douyin_cancel_request.py
dg_sdk/request/v2_coupon_douyin_certificate_query_request.py
dg_sdk/request/v2_coupon_douyin_consume_request.py
dg_sdk/request/v2_coupon_douyin_prepare_request.py
dg_sdk/request/v2_coupon_douyin_product_query_request.py
dg_sdk/request/v2_coupon_meal_query_request.py
dg_sdk/request/v2_coupon_meituan_cancel_request.py
dg_sdk/request/v2_coupon_meituan_consume_request.py
dg_sdk/request/v2_coupon_meituan_prepare_request.py
dg_sdk/request/v2_coupon_meituan_query_request.py
dg_sdk/request/v2_coupon_shopdeal_query_request.py
dg_sdk/request/v2_efp_acctpayment_refund_query_request.py
dg_sdk/request/v2_efp_acctpayment_refund_request.py
dg_sdk/request/v2_efp_encash_request.py
dg_sdk/request/v2_efp_surrogate_request.py
dg_sdk/request/v2_efp_withdraw_query_request.py
dg_sdk/request/v2_flexible_ent_modify_request.py
dg_sdk/request/v2_flexible_ent_query_request.py
dg_sdk/request/v2_flexible_ent_request.py
dg_sdk/request/v2_flexible_indv_modify_request.py
dg_sdk/request/v2_flexible_indv_query_request.py
dg_sdk/request/v2_flexible_indv_request.py
