Metadata-Version: 2.1
Name: dg-sdk
Version: 2.0.17
Summary: 汇付天下为了提高客户的接入体验，特提供封装的开发SDK，使用本SDK将极大的简化开发者的工作，开发者将无需考虑通信、签名、验签等，只需要关注业务参数的拼装
Home-page: https://paas.huifu.com/
Author: huifu developers
Author-email: yingyong.wang@huifu.com
License: UNKNOWN
Platform: UNKNOWN
Classifier: Development Status :: 4 - Beta
Classifier: Intended Audience :: Developers
Classifier: Topic :: Software Development :: Build Tools
Classifier: License :: OSI Approved :: MIT License
Classifier: Programming Language :: Python
Classifier: Programming Language :: Python :: 3.5
Classifier: Programming Language :: Python :: 3.6
Classifier: Programming Language :: Python :: 3.7
